[
  {
    "ID":"01",
    "name":"Толкачева Б.З.",
    "position":"Уборщик"
  },

  {
    "ID":"02",
    "name":"Яруллин А.Н.",
    "position":"Уборщик"
  },

  {
    "ID":"03",
    "name":"Яруллина В.Д.",
    "position":"Водитель"
  },

  {
    "ID":"04",
    "name":"Соловьев Б.Н.",
    "position":"Водитель"
  },

  {
    "ID":"05",
    "name":"Харьков Т.К.",
    "position":"Программист"
  },

  {
    "ID":"06",
    "name":"Любова А.В.",
    "position":"Программист"
  },

  {
    "ID":"07",
    "name":"Жданова К.М.",
    "position":"Программист"
  },

  {
    "ID":"08",
    "name":"Бойцов К.И.",
    "position":"Программист"
  },

  {
    "ID":"09",
    "name":"Лоськова Р.В.",
    "position":"Программист"
  },

  {
    "ID":"10",
    "name":"Смолина Е.В.",
    "position":"Программист"
  },

  {
    "ID":"11",
    "name":"Чмыхов Р.Д.",
    "position":"Тестировщик"
  },

  {
    "ID":"12",
    "name":"Нутрихина П.В.",
    "position":"Тестировщик"
  },

  {
    "ID":"13",
    "name":"Щавлева С.Ю.",
    "position":"Тестировщик"
  },

  {
    "ID":"14",
    "name":"Эсаулов А.К.",
    "position":"Тестировщик"
  },

  {
    "ID":"15",
    "name":"Аникина А.Л.",
    "position":"Тестировщик"
  },

  {
    "ID":"16",
    "name":"Язынина А.Ф.",
    "position":"Тестировщик"
  },

  {
    "ID":"17",
    "name":"Таланина П.К.",
    "position":"Тимлид"
  },

  {
    "ID":"18",
    "name":"Астанков К.М.",
    "position":"Тимлид"
  },

  {
    "ID":"19",
    "name":"Петрищев А.П.",
    "position":"Менеджер"
  },

  {
    "ID":"20",
    "name":"Мишин О.Н.",
    "position":"Менеджер"
  },

  {
    "ID":"21",
    "name":"Кудашова Р.Д.",
    "position":"Менеджер"
  },

  {
    "ID":"22",
    "name":"Жолдина Д.Б.",
    "position":"Менеджер"
  },

  {
    "ID":"23",
    "name":"Землякова М.П.",
    "position":"Менеджер"
  },

  {
    "ID":"24",
    "name":"Брежнева В.Д.",
    "position":"Менеджер"
  },

  {
    "ID":"25",
    "name":"Арчибасов Д.И.",
    "position":"Менеджер проекта"
  },

  {
    "ID":"26",
    "name":"Кудров Н.А.",
    "position":"Менеджер проекта"
  },

  {
    "ID":"27",
    "name":"Савкин Е.В.",
    "position":"Водитель"
  },

  {
    "ID":"28",
    "name":"Шубина Р.Н.",
    "position":"Уборщик"
  },

  {
    "ID":"29",
    "name":"Арсьеньев Л.А.",
    "position":"Программист"
  },

  {
    "ID":"30",
    "name":"Рамаев А.Д.",
    "position":"Сеньор менеджер"
  }
]